pyaslengine/__init__.py
pyaslengine/aws/services/__init__.py
pyaslengine/aws/services/base.py
pyaslengine/aws/services/ecs.py
pyaslengine/aws/services/lambdas.py
pyaslengine/aws/services/sns.py
pyaslengine/data.py
pyaslengine/exceptions.py
pyaslengine/log.py
pyaslengine/patch/__init__.py
pyaslengine/patch/decorators.py
pyaslengine/patch/resources.py
pyaslengine/patch/states.py
pyaslengine/rules.py
pyaslengine/schemas.py
pyaslengine/states.py
pyaslengine/workflows.py
pyaslengine-0.8.0.dist-info/LICENSE
pyaslengine-0.8.0.dist-info/METADATA
pyaslengine-0.8.0.dist-info/WHEEL
pyaslengine-0.8.0.dist-info/RECORD
