Metadata-Version: 2.1
Name: pyaslengine
Version: 0.8.0
Summary: Python engine for Amazon States Language (ASL) specification that supports parsing and serialization of definitions, and a local interpreter to run them.
Home-page: https://github.com/ghukill/pyaslengine
Author: Graham Hukill
Author-email: ghukill@gmail.com
Requires-Python: >=3.11,<4.0
Classifier: Programming Language :: Python :: 3
Classifier: Programming Language :: Python :: 3.11
Classifier: Programming Language :: Python :: 3.12
Requires-Dist: attrs (>=23.1.0,<24.0.0)
Requires-Dist: boto3 (>=1.29.6,<2.0.0)
Requires-Dist: jsonpath-ng (>=1.6.0,<2.0.0)
Requires-Dist: marshmallow (>=3.20.1,<4.0.0)
